kinto_algolia/__init__.py
kinto_algolia/command_reindex.py
kinto_algolia/indexer.py
kinto_algolia/listener.py
kinto_algolia/utils.py
kinto_algolia/views.py
kinto_algolia-1.1.0.dist-info/LICENSE
kinto_algolia-1.1.0.dist-info/METADATA
kinto_algolia-1.1.0.dist-info/WHEEL
kinto_algolia-1.1.0.dist-info/entry_points.txt
kinto_algolia-1.1.0.dist-info/top_level.txt
kinto_algolia-1.1.0.dist-info/RECORD
