Metadata-Version: 2.1
Name: kinto-algolia
Version: 1.1.0
Summary: Index and search records using Algolia.
Home-page: https://github.com/Kinto/kinto-algolia
Author: Rémy Hubscher
Author-email: hubscher.remy@gmail.com
License: Apache License (2.0)
Keywords: kinto algolia index
Platform: UNKNOWN
Classifier: Development Status :: 2 - Pre-Alpha
Classifier: Intended Audience :: Developers
Classifier: License :: OSI Approved :: Apache Software License
Classifier: Natural Language :: English
Classifier: Programming Language :: Python :: 3
Classifier: Programming Language :: Python :: 3.5
Classifier: Programming Language :: Python :: 3.6
Requires-Dist: algoliasearch
Requires-Dist: kinto
